astro_rubix-0.0.4.dist-info/licenses/LICENSE.md
rubix/__init__.py
rubix/_version.py
rubix/logger.py
rubix/paths.py
rubix/units.py
rubix/utils.py
rubix/config/config.py
rubix/config/pipeline_config.yml
rubix/config/pynbody_config.yml
rubix/config/rubix_config.yml
rubix/core/__init__.py
rubix/core/cosmology.py
rubix/core/data.py
rubix/core/dust.py
rubix/core/fits.py
rubix/core/ifu.py
rubix/core/lsf.py
rubix/core/noise.py
rubix/core/pipeline.py
rubix/core/psf.py
rubix/core/rotation.py
rubix/core/ssp.py
rubix/core/telescope.py
rubix/core/visualisation.py
rubix/cosmology/__init__.py
rubix/cosmology/base.py
rubix/cosmology/utils.py
rubix/galaxy/__init__.py
rubix/galaxy/alignment.py
rubix/galaxy/input_handler/__init__.py
rubix/galaxy/input_handler/base.py
rubix/galaxy/input_handler/factory.py
rubix/galaxy/input_handler/illustris.py
rubix/galaxy/input_handler/pynbody.py
rubix/galaxy/input_handler/api/illustris_api.py
rubix/pipeline/__init__.py
rubix/pipeline/abstract_pipeline.py
rubix/pipeline/linear_pipeline.py
rubix/pipeline/transformer.py
rubix/spectra/__init__.py
rubix/spectra/ifu.py
rubix/spectra/dust/dust_baseclasses.py
rubix/spectra/dust/dust_extinction.py
rubix/spectra/dust/extinction_models.py
rubix/spectra/dust/generic_models.py
rubix/spectra/dust/helpers.py
rubix/spectra/ssp/__init__.py
rubix/spectra/ssp/factory.py
rubix/spectra/ssp/fsps_grid.py
rubix/spectra/ssp/grid.py
rubix/spectra/ssp/templates.py
rubix/spectra/ssp/templates/BC03lr.h5
rubix/telescope/__init__.py
rubix/telescope/apertures.py
rubix/telescope/base.py
rubix/telescope/factory.py
rubix/telescope/telescopes.yaml
rubix/telescope/utils.py
rubix/telescope/filters/__init__.py
rubix/telescope/filters/filters.py
rubix/telescope/lsf/__init__.py
rubix/telescope/lsf/lsf.py
rubix/telescope/noise/__init__.py
rubix/telescope/noise/noise.py
rubix/telescope/psf/__init__.py
rubix/telescope/psf/kernels.py
rubix/telescope/psf/psf.py
astro_rubix-0.0.4.dist-info/METADATA
astro_rubix-0.0.4.dist-info/WHEEL
astro_rubix-0.0.4.dist-info/top_level.txt
astro_rubix-0.0.4.dist-info/RECORD
