Metadata-Version: 2.4
Name: astro-rubix
Version: 0.0.4
Summary: A toolkit for simulating and analyzing integral field spectroscopic data cubes of astronomical sources.
Author-email: AstroAI-Lab <astroai@iwr.uni-heidelberg.de>, Tobias Buck <tobias.buck@iwr.uni-heidelberg.de>, Ufuk Cakir <ufukcakir@robots.ox.ac.uk>, Anna Lena Schaible <annalena.schaible@iwr.uni-heidelberg.de>
Maintainer-email: AstroAI-Lab <astroai@iwr.uni-heidelberg.de>
License: MIT
Project-URL: Homepage, https://astro-rubix.web.app
Project-URL: Repository, https://github.com/AstroAI-Lab/rubix
Project-URL: Issues, https://github.com/AstroAI-Lab/rubix/issues
Keywords: galaxy,modelling,smoothed particle hydrodynamics,particles,nbody,galaxy formation,parametric,theory,sph,cosmology,galaxy evolution,survey,telescope,stellar population,synthesis,IFU,integral field unit,astronomy,astrophysics,simulation,JAX,differentiable programming,automatic differentiation,machine learning,GPU
Classifier: Programming Language :: Python :: 3
Classifier: Operating System :: OS Independent
Classifier: License :: OSI Approved :: MIT License
Requires-Python: >=3.11
License-File: LICENSE.md
Requires-Dist: jax[cpu]>0.5.1
Requires-Dist: requests
Requires-Dist: h5py
Requires-Dist: astropy
Requires-Dist: scipy
Requires-Dist: numpy
Requires-Dist: matplotlib
Requires-Dist: pyaml
Requires-Dist: jaxtyping
Requires-Dist: equinox
Requires-Dist: interpax
Requires-Dist: astroquery
Requires-Dist: beartype
Requires-Dist: mpdaf
Requires-Dist: ipywidgets
Requires-Dist: jdaviz
Requires-Dist: pynbody
Requires-Dist: optax
Requires-Dist: opt-einsum>=3.3.0
Provides-Extra: dev
Requires-Dist: black; extra == "dev"
Requires-Dist: pre-commit; extra == "dev"
Requires-Dist: nbstripout; extra == "dev"
Provides-Extra: tests
Requires-Dist: pytest; extra == "tests"
Requires-Dist: pytest-cov; extra == "tests"
Requires-Dist: pytest-mock; extra == "tests"
Requires-Dist: requests-mock; extra == "tests"
Requires-Dist: nbval; extra == "tests"
Requires-Dist: pre-commit; extra == "tests"
Provides-Extra: docs
Requires-Dist: ipykernel; extra == "docs"
Requires-Dist: nbsphinx; extra == "docs"
Requires-Dist: nbsphinx-link; extra == "docs"
Requires-Dist: sphinx; extra == "docs"
Requires-Dist: sphinx_mdinclude; extra == "docs"
Requires-Dist: sphinx_rtd_theme; extra == "docs"
Provides-Extra: cuda
Requires-Dist: jax[cuda]>0.5.1; extra == "cuda"
Dynamic: license-file
